{
    "trackLyrics": {
        "syncType": "UNSYNCED",
        "lines": [
            {
                "startTimeMs": "0",
                "words": "Io che, quando recito, scordo le frasi",
                "syllables": []
            },
            {
                "startTimeMs": "0",
                "words": "Perché non c'è un ruolo che sappia indossare",
                "syllables": []
            },
            {
                "startTimeMs": "0",
                "words": "La strada che ho scelto è la stessa di allora",
                "syllables": []
            },
            {
                "startTimeMs": "0",
                "words": "Non voglio una vita semplice, Io grido ancora",
                "syllables": []
            },
            {
                "startTimeMs": "0",
                "words": "Sai, mentre ti guardo io fermerei il tempo",
                "syllables": []
            },
            {
                "startTimeMs": "0",
                "words": "Tu sei la risata di un uomo che ha perso",
                "syllables": []
            },
            {
                "startTimeMs": "0",
                "words": "Tu sei la carezza che resta sul viso",
                "syllables": []
            },
            {
                "startTimeMs": "0",
                "words": "Quando la notte mi alzo e mi manca il respiro",
                "syllables": []
            },
            {
                "startTimeMs": "0",
                "words": "E sono sempre io che rovino tutto sul finale",
                "syllables": []
            },
            {
                "startTimeMs": "0",
                "words": "Che allontano le persone",
                "syllables": []
            },
            {
                "startTimeMs": "0",
                "words": "Ma poi da solo non ci riesco a stare",
                "syllables": []
            },
            {
                "startTimeMs": "0",
                "words": "E poi d'inverno voglio indietro il mare",
                "syllables": []
            },
            {
                "startTimeMs": "0",
                "words": "Ma poi d'estate non mi basta il sole",
                "syllables": []
            },
            {
                "startTimeMs": "0",
                "words": "Tanto lo so che resta sempre uguale",
                "syllables": []
            },
            {
                "startTimeMs": "0",
                "words": "Tu resti bella anche se mi fai male, mhm",
                "syllables": []
            },
            {
                "startTimeMs": "0",
                "words": "♪",
                "syllables": []
            },
            {
                "startTimeMs": "0",
                "words": "Io che non so vivere senza sognare",
                "syllables": []
            },
            {
                "startTimeMs": "0",
                "words": "Guardarsi allo specchio e ritrovarsi a volare",
                "syllables": []
            },
            {
                "startTimeMs": "0",
                "words": "Lasciatemi un filo dove poter camminare",
                "syllables": []
            },
            {
                "startTimeMs": "0",
                "words": "Tenetevi il mondo e lasciatemi il mare",
                "syllables": []
            },
            {
                "startTimeMs": "0",
                "words": "E mentre qui piove poi ascolto le gocce",
                "syllables": []
            },
            {
                "startTimeMs": "0",
                "words": "Posarsi sul dorso di strade deserte",
                "syllables": []
            },
            {
                "startTimeMs": "0",
                "words": "Il vento è il consiglio che devi sentire",
                "syllables": []
            },
            {
                "startTimeMs": "0",
                "words": "Non essere mai come gli altri, continualo a dire",
                "syllables": []
            },
            {
                "startTimeMs": "0",
                "words": "E sono sempre io che rovino tutto sul finale",
                "syllables": []
            },
            {
                "startTimeMs": "0",
                "words": "Che allontano le persone",
                "syllables": []
            },
            {
                "startTimeMs": "0",
                "words": "Ma poi da solo non ci riesco a stare",
                "syllables": []
            },
            {
                "startTimeMs": "0",
                "words": "E poi d'inverno voglio indietro il mare",
                "syllables": []
            },
            {
                "startTimeMs": "0",
                "words": "Ma poi d'estate non mi basta il sole",
                "syllables": []
            },
            {
                "startTimeMs": "0",
                "words": "Tanto lo so che resta sempre uguale",
                "syllables": []
            },
            {
                "startTimeMs": "0",
                "words": "Tu resti bella anche se mi fai male, oh",
                "syllables": []
            },
            {
                "startTimeMs": "0",
                "words": "♪",
                "syllables": []
            },
            {
                "startTimeMs": "0",
                "words": "Sei nel sole che brucia, ma che cerco ancora",
                "syllables": []
            },
            {
                "startTimeMs": "0",
                "words": "Sei nel vuoto che uccide, ma riempie qualcosa",
                "syllables": []
            },
            {
                "startTimeMs": "0",
                "words": "E sei fra tutti i miei vizi che rimpiango nel letto",
                "syllables": []
            },
            {
                "startTimeMs": "0",
                "words": "Quando il cuore è veloce e la notte non dormo",
                "syllables": []
            },
            {
                "startTimeMs": "0",
                "words": "E sei fra quelle risate che non tornano più",
                "syllables": []
            },
            {
                "startTimeMs": "0",
                "words": "Perché tu mi fai male, ma sei sempre tu",
                "syllables": []
            },
            {
                "startTimeMs": "0",
                "words": "E promettimi adesso che saprai sentirti",
                "syllables": []
            },
            {
                "startTimeMs": "0",
                "words": "Non essere mai come gli altri",
                "syllables": []
            },
            {
                "startTimeMs": "0",
                "words": "Tu devi riuscirci, tu devi riuscirci",
                "syllables": []
            },
            {
                "startTimeMs": "0",
                "words": "E sono sempre io che rovino tutto sul finale",
                "syllables": []
            },
            {
                "startTimeMs": "0",
                "words": "Che allontano le persone",
                "syllables": []
            },
            {
                "startTimeMs": "0",
                "words": "Ma poi da solo non ci riesco a stare",
                "syllables": []
            },
            {
                "startTimeMs": "0",
                "words": "E poi d'inverno voglio indietro il mare",
                "syllables": []
            },
            {
                "startTimeMs": "0",
                "words": "Ma poi d'estate non mi basta il sole",
                "syllables": []
            },
            {
                "startTimeMs": "0",
                "words": "Tanto lo so che resta sempre uguale",
                "syllables": []
            },
            {
                "startTimeMs": "0",
                "words": "Tu resti bella anche se mi fai male, oh",
                "syllables": []
            },
            {
                "startTimeMs": "0",
                "words": "Tu resti bella anche se mi fai male, oh",
                "syllables": []
            },
            {
                "startTimeMs": "0",
                "words": "Tu resti bella anche se mi fai male, oh",
                "syllables": []
            },
            {
                "startTimeMs": "0",
                "words": "",
                "syllables": []
            }
        ],
        "provider": "MusixMatch",
        "providerLyricsId": "141404195",
        "providerDisplayName": "Musixmatch",
        "syncLyricsUri": "",
        "isDenseTypeface": false,
        "alternatives": [],
        "language": "it",
        "isRtlLanguage": false,
        "fullscreenAction": "FULLSCREEN_LYRICS"
    },
    "trackInfo": {
        "album": {
            "album_type": "album",
            "artists": [
                {
                    "external_urls": {
                        "spotify": "https://open.spotify.com/artist/3hN3iJMbbBmqBSAMx5veDa"
                    },
                    "href": "https://api.spotify.com/v1/artists/3hN3iJMbbBmqBSAMx5veDa",
                    "id": "3hN3iJMbbBmqBSAMx5veDa",
                    "name": "Ultimo",
                    "type": "artist",
                    "uri": "spotify:artist:3hN3iJMbbBmqBSAMx5veDa"
                }
            ],
            "available_markets": [
                "AD",
                "AE",
                "AG",
                "AL",
                "AM",
                "AO",
                "AR",
                "AT",
                "AU",
                "AZ",
                "BA",
                "BB",
                "BD",
                "BE",
                "BF",
                "BG",
                "BH",
                "BI",
                "BJ",
                "BN",
                "BO",
                "BR",
                "BS",
                "BT",
                "BW",
                "BY",
                "BZ",
                "CA",
                "CD",
                "CG",
                "CH",
                "CI",
                "CL",
                "CM",
                "CO",
                "CR",
                "CV",
                "CW",
                "CY",
                "CZ",
                "DE",
                "DJ",
                "DK",
                "DM",
                "DO",
                "DZ",
                "EC",
                "EE",
                "EG",
                "ES",
                "FI",
                "FJ",
                "FM",
                "FR",
                "GA",
                "GB",
                "GD",
                "GE",
                "GH",
                "GM",
                "GN",
                "GQ",
                "GR",
                "GT",
                "GW",
                "GY",
                "HK",
                "HN",
                "HR",
                "HT",
                "HU",
                "ID",
                "IE",
                "IL",
                "IN",
                "IQ",
                "IS",
                "IT",
                "JM",
                "JO",
                "JP",
                "KE",
                "KG",
                "KH",
                "KI",
                "KM",
                "KN",
                "KR",
                "KW",
                "KZ",
                "LA",
                "LB",
                "LC",
                "LI",
                "LK",
                "LR",
                "LS",
                "LT",
                "LU",
                "LV",
                "LY",
                "MA",
                "MC",
                "MD",
                "ME",
                "MG",
                "MH",
                "MK",
                "ML",
                "MN",
                "MO",
                "MR",
                "MT",
                "MU",
                "MV",
                "MW",
                "MX",
                "MY",
                "MZ",
                "NA",
                "NE",
                "NG",
                "NI",
                "NL",
                "NO",
                "NP",
                "NR",
                "NZ",
                "OM",
                "PA",
                "PE",
                "PG",
                "PH",
                "PK",
                "PL",
                "PS",
                "PT",
                "PW",
                "PY",
                "QA",
                "RO",
                "RS",
                "RW",
                "SA",
                "SB",
                "SC",
                "SE",
                "SG",
                "SI",
                "SK",
                "SL",
                "SM",
                "SN",
                "SR",
                "ST",
                "SV",
                "SZ",
                "TD",
                "TG",
                "TH",
                "TJ",
                "TL",
                "TN",
                "TO",
                "TR",
                "TT",
                "TV",
                "TW",
                "TZ",
                "UA",
                "UG",
                "US",
                "UY",
                "UZ",
                "VC",
                "VE",
                "VN",
                "VU",
                "WS",
                "XK",
                "ZA",
                "ZM",
                "ZW"
            ],
            "external_urls": {
                "spotify": "https://open.spotify.com/album/2p0A6scqcnQtnRDBhOgCGg"
            },
            "href": "https://api.spotify.com/v1/albums/2p0A6scqcnQtnRDBhOgCGg",
            "id": "2p0A6scqcnQtnRDBhOgCGg",
            "images": [
                {
                    "height": 640,
                    "url": "https://i.scdn.co/image/ab67616d0000b273d3b4727114f28a7dec313ece",
                    "width": 640
                },
                {
                    "height": 300,
                    "url": "https://i.scdn.co/image/ab67616d00001e02d3b4727114f28a7dec313ece",
                    "width": 300
                },
                {
                    "height": 64,
                    "url": "https://i.scdn.co/image/ab67616d00004851d3b4727114f28a7dec313ece",
                    "width": 64
                }
            ],
            "name": "Solo - Home piano session",
            "release_date": "2022-03-25",
            "release_date_precision": "day",
            "total_tracks": 24,
            "type": "album",
            "uri": "spotify:album:2p0A6scqcnQtnRDBhOgCGg"
        },
        "artists": [
            {
                "external_urls": {
                    "spotify": "https://open.spotify.com/artist/3hN3iJMbbBmqBSAMx5veDa"
                },
                "href": "https://api.spotify.com/v1/artists/3hN3iJMbbBmqBSAMx5veDa",
                "id": "3hN3iJMbbBmqBSAMx5veDa",
                "name": "Ultimo",
                "type": "artist",
                "uri": "spotify:artist:3hN3iJMbbBmqBSAMx5veDa"
            }
        ],
        "available_markets": [
            "AD",
            "AE",
            "AG",
            "AL",
            "AM",
            "AO",
            "AR",
            "AT",
            "AU",
            "AZ",
            "BA",
            "BB",
            "BD",
            "BE",
            "BF",
            "BG",
            "BH",
            "BI",
            "BJ",
            "BN",
            "BO",
            "BR",
            "BS",
            "BT",
            "BW",
            "BY",
            "BZ",
            "CA",
            "CD",
            "CG",
            "CH",
            "CI",
            "CL",
            "CM",
            "CO",
            "CR",
            "CV",
            "CW",
            "CY",
            "CZ",
            "DE",
            "DJ",
            "DK",
            "DM",
            "DO",
            "DZ",
            "EC",
            "EE",
            "EG",
            "ES",
            "FI",
            "FJ",
            "FM",
            "FR",
            "GA",
            "GB",
            "GD",
            "GE",
            "GH",
            "GM",
            "GN",
            "GQ",
            "GR",
            "GT",
            "GW",
            "GY",
            "HK",
            "HN",
            "HR",
            "HT",
            "HU",
            "ID",
            "IE",
            "IL",
            "IN",
            "IQ",
            "IS",
            "IT",
            "JM",
            "JO",
            "JP",
            "KE",
            "KG",
            "KH",
            "KI",
            "KM",
            "KN",
            "KR",
            "KW",
            "KZ",
            "LA",
            "LB",
            "LC",
            "LI",
            "LK",
            "LR",
            "LS",
            "LT",
            "LU",
            "LV",
            "LY",
            "MA",
            "MC",
            "MD",
            "ME",
            "MG",
            "MH",
            "MK",
            "ML",
            "MN",
            "MO",
            "MR",
            "MT",
            "MU",
            "MV",
            "MW",
            "MX",
            "MY",
            "MZ",
            "NA",
            "NE",
            "NG",
            "NI",
            "NL",
            "NO",
            "NP",
            "NR",
            "NZ",
            "OM",
            "PA",
            "PE",
            "PG",
            "PH",
            "PK",
            "PL",
            "PS",
            "PT",
            "PW",
            "PY",
            "QA",
            "RO",
            "RS",
            "RW",
            "SA",
            "SB",
            "SC",
            "SE",
            "SG",
            "SI",
            "SK",
            "SL",
            "SM",
            "SN",
            "SR",
            "ST",
            "SV",
            "SZ",
            "TD",
            "TG",
            "TH",
            "TJ",
            "TL",
            "TN",
            "TO",
            "TR",
            "TT",
            "TV",
            "TW",
            "TZ",
            "UA",
            "UG",
            "US",
            "UY",
            "UZ",
            "VC",
            "VE",
            "VN",
            "VU",
            "WS",
            "XK",
            "ZA",
            "ZM",
            "ZW"
        ],
        "disc_number": 1,
        "duration_ms": 236617,
        "explicit": false,
        "external_ids": {
            "isrc": "ITU7T2200006"
        },
        "external_urls": {
            "spotify": "https://open.spotify.com/track/377NnMMxLvffWCcSIT4W20"
        },
        "href": "https://api.spotify.com/v1/tracks/377NnMMxLvffWCcSIT4W20",
        "id": "377NnMMxLvffWCcSIT4W20",
        "is_local": false,
        "name": "Sul finale - Home piano session",
        "popularity": 38,
        "preview_url": "https://p.scdn.co/mp3-preview/237b7335ee67eff26fe5c7c85e2c90b0f070cab8?cid=774b29d4f13844c495f206cafdad9c86",
        "track_number": 7,
        "type": "track",
        "uri": "spotify:track:377NnMMxLvffWCcSIT4W20"
    }
}